{
  "code": "3619cr",
  "page": "P.11",
  "text": "ebelgre Tuke a momer to tell us about our smoking preferences Pni coecons be Please ta.oner 5070603507726545 the posiagt. rh SUEJn Je' Ms.anga S/Pist usma uncerstand begible 3619cr n Ay smcl.ers.Anc, Dal C% 75200 Bydg whn eder ca milf-t7ya Bith Signaturerqurred: Da ca 12 your egat ra wee not vallable.what otber branswow consider ting Cheee afl tar app'y! CAltae D Paamen Bas 20 Chaekor Heoge nG.. Chr#..c! Ca Mre - Chko Medium - OFull flavy LghM.id No B 3.r pa e trand pa dou  cch bunde 1 syca =* #Packs revous braad brang #o Packs brand #of Pack * hat would you do #ol Packs eC a5 Asn enr CAmnan lnn DOter odrr wwwwgameb.s u hosd 21 yearndern prna bhdate and cupons rcg nen ey ar erm luons to by ngare MI Lasi Nune.yawr Reguiar Erand hhr cn.eccing-rdermaton ! pcial offer FNGTL csoket arbrand 3N p your nght to smcke ced in Joning smskers Hi. C C 2044934418",
  "survey": {
    "question": "ebelgre Tuke a momer to tell us about our smoking preferences",
    "options": []
  },
  "id": "3619cr",
  "position": "n Ay",
  "response": null,
  "name": "Ms.anga S/Pist",
  "initials": "S/Pist",
  "contact": "5070603507726545",
  "understanding": "uncerstand",
  "legibility": "begible",
  "code2": "3619cr",
  "location": "n Ay",
  "smokers": "smcl.ers.Anc",
  "data": {
    "Dal": "C%",
    "code3": "75200",
    "Bydg": "Bydg whn",
    "eder": "eder",
    "birth": "Bith"
  },
  "signature": {
    "required": "signaturerqurred",
    "date": null
  },
  "legal": {
    "age": "21",
    "brands": "Cheee afl tar app'y"
  },
  "application": null,
  "code4": "#Packs",
  "payment": {
    "base": "Bas",
    "method": "Chaekor",
    "check": "Heoge",
    "hedge": "nG",
    "number": "20"
  },
  "characteristics": {
    "chr": "Chr#",
    "c": "c!",
    "ca": "Ca Mre",
    "medium": "Medium",
    "full_flavor": "OFull flavy",
    "light": "LghM.id",
    "no": "No B",
    "b": "3.r pa e trand pa dou  cch bunde 1 syca =* #Packs"
  },
  "packs": {
    "count": "#Packs",
    "type": "revous braad brang",
    "trand": "trand",
    "bundle": "cch bunde",
    "syca": "syca",
    "code5": "#o Packs",
    "symbol": "*"
  },
  "previous_brand": {
    "packs": "#ol Packs",
    "brand": null,
    "brand_count": null,
    "pack_count": null,
    "brand2": null,
    "pack_count2": null
  },
  "action": {
    "question": "hat would you do",
    "pack_count3": "#ol Packs"
  },
  "code6": "3619cr",
  "code7": "#o Packs",
  "asn": "enr CAmnan lnn",
  "company": "DOter odrr",
  "other": "wwgameb.s u hosd 21 yearndern prna bhdate and cupons rcg nen ey ar erm luons to by ngare MI Lasi Nune.yawr",
  "order": "MI Lasi Nune.yawr",
  "game": "wwgameb.s",
  "age_requirement": "21",
  "birthdate": null,
  "coupons": "cupons rcg nen ey ar erm luons to by ngare MI Lasi Nune.yawr",
  "terms": "MI Lasi Nune.yawr",
  "purchase": "MI Lasi Nune.yawr",
  "mi": "MI Lasi Nune.yawr",
  "last_name": "Ms.anga S/Pist",
  "year": null,
  "regular_brand": "Reguiar Erand",
  "hhr": "cn.eccing-rdermaton",
  "checking": "pcial offer",
  "special_offer": "FNGTL csoket arbrand 3N p",
  "code8": "3N",
  "cigarette": "ebelgre",
  "brand": "ebelgre",
  "code9": "3N",
  "p": "p",
  "right": "your nght to smcke ced in Joning smskers",
  "joining": "Hi. C C 2044934418",
  "hi": "Hi. C C 2044934418",
  "code10": "2044934418",
  "code11": "3N",
  "number2": "2044934418"
}